README.rst
setup.py
simplescript.py
simplescript.egg-info/PKG-INFO
simplescript.egg-info/SOURCES.txt
simplescript.egg-info/dependency_links.txt
simplescript.egg-info/top_level.txt