Metadata-Version: 1.1
Name: simplescript
Version: 0.1
Summary: Make shell scripts from python functions
Home-page: https://github.com/NegativeMjark/simplescript
Author: Mark Haines
Author-email: mjark@negativecurvature.net
License: Apache License, Version 2.0
Keywords: script shell
Platform: UNKNOWN
Classifier: Development Status :: 3 - Alpha
Classifier: Intended Audience :: Developers
Classifier: License :: OSI Approved :: Apache Software License
Classifier: Programming Language :: Python :: 2
